LICENSE
README.md
pyproject.toml
setup.py
src/csclib/BP.h
src/csclib/LOUDS.h
src/csclib/__init__.py
src/csclib/beaver.h
src/csclib/bits.h
src/csclib/bits_tools.h
src/csclib/block_dshare.h
src/csclib/block_share.h
src/csclib/comm.h
src/csclib/compare.h
src/csclib/dshare.h
src/csclib/evaluation.h
src/csclib/field.h
src/csclib/func.h
src/csclib/groupedvector.h
src/csclib/mman.h
src/csclib/mpc.h
src/csclib/mt.h
src/csclib/precompute.h
src/csclib/pycsclib.c
src/csclib/pycsclib.py
src/csclib/random.h
src/csclib/rss.h
src/csclib/shamir.h
src/csclib/share.h
src/csclib/share_core.h
src/csclib/suffixarray.h
src/csclib/unitv.h
src/csclib.egg-info/PKG-INFO
src/csclib.egg-info/SOURCES.txt
src/csclib.egg-info/dependency_links.txt
src/csclib.egg-info/top_level.txt
src/csclib/LOUDS/LOUDS.py
src/csclib/LOUDS/__init__.py
src/csclib/SA/__init__.py
src/csclib/SA/suffixarray.py
src/csclib/SA/test1.py
src/csclib/SA/test2.py
tests/test1.py
tests/test2.py
tests/test3.py
tests/test4.py