Metadata-Version: 2.4
Name: csclib
Version: 202601191
Summary: csclib
Author-email: Kunihiko Sadakane <sada@mist.i.u-tokyo.ac.jp>
License-File: LICENSE
Dynamic: license-file
